dnv/__init__.py
dnv/sesamx/__init__.py
dnv/sesamx/load_assemblies.py
dnv/sesamx/runtimeconfig.json
dnv/sesamx/workspace_utils.py
dnv/sesamx/.dlls/DNV.ApplicationVersionManager.Core.dll
dnv_sesamx-1.0.3.dist-info/licenses/LICENSE
dnv_sesamx-1.0.3.dist-info/METADATA
dnv_sesamx-1.0.3.dist-info/WHEEL
dnv_sesamx-1.0.3.dist-info/top_level.txt
dnv_sesamx-1.0.3.dist-info/RECORD
