Metadata-Version: 2.4
Name: dnv-sesamx
Version: 1.0.3
Summary: Python library for developing and running SesamX workflows.
Author-email: DNV <software.support@dnv.com>
Project-URL: Homepage, https://sesam.dnv.com
Keywords: sesamx,sesam,workflow
Classifier: Development Status :: 4 - Beta
Classifier: License :: OSI Approved :: MIT License
Classifier: Programming Language :: Python
Classifier: Programming Language :: Python :: 3.10
Requires-Python: >=3.10
License-File: LICENSE
Requires-Dist: pythonnet==3.0.5
Dynamic: license-file
